image/__init__.py
image/admins.py
image/apps.py
image/checks.py
image/constants.py
image/decisions.py
image/decorators.py
image/filters.py
image/filters_pillow.py
image/filters_wand.py
image/form_fields.py
image/forms.py
image/image_filters.py
image/image_ops_pillow.py
image/image_ops_wand.py
image/model_fields.py
image/models.py
image/module_loading.py
image/module_utils.py
image/registry.py
image/settings.py
image/shortcuts.py
image/signals.py
image/utils.py
image/validators.py
image/views.py
image/management/commands/common.py
image/management/commands/image_create_bulk.py
image/management/commands/image_delete.py
image/management/commands/image_list.py
image/management/commands/image_sync.py
image/management/commands/reform_delete.py
image/management/commands/reform_list.py
image/migrations/0001_initial.py
image/migrations/__init__.py
image/static/image/unfound.jpg
image/static/image/unfound.png
image/static/image/unfound2.png
image/static/image/watermark.png
image/static/image/css/forms.css
image/templates/image/image_detail.html
image/templates/image/reforms_addform.html
image/templatetags/__init__.py
image/templatetags/img_tags.py
image/test_image/admin.py
image/test_image/apps.py
image/test_image/models.py
image/test_image/views.py
image/test_image/migrations/0001_initial.py
image/test_image/migrations/__init__.py
image/test_image/tests/__init__.py
image/test_image/tests/fixture_wanf_filter.py
image/test_image/tests/test_broken.py
image/test_image/tests/test_commands.py
image/test_image/tests/test_decisions.py
image/test_image/tests/test_filters.py
image/test_image/tests/test_image.py
image/test_image/tests/test_image_subclass.py
image/test_image/tests/test_model_fields.py
image/test_image/tests/test_module_utils.py
image/test_image/tests/test_reform.py
image/test_image/tests/test_registry.py
image/test_image/tests/test_settings.py
image/test_image/tests/test_tags.py
image/test_image/tests/test_validators.py
image/test_image/tests/utils.py
django_img-0.1.5.dist-info/LICENSE
django_img-0.1.5.dist-info/WHEEL
django_img-0.1.5.dist-info/METADATA
django_img-0.1.5.dist-info/RECORD
