Metadata-Version: 2.1
Name: django-img
Version: 0.1.5
Summary: Image handling for Django. Includes upload code, repository and filter creation. Low on features, fast setup, modular.
Home-page: https://github.com/rcrowther/django-image
License: UNKNOWN
Author: robert crowther
Author-email: rw.crowther@gmail.com
Classifier: Operating System :: OS Independent
Classifier: License :: OSI Approved :: BSD License
Classifier: Programming Language :: Python :: 3
Classifier: Framework :: Django
Requires-Dist: unidecode
